README.md
setup.py
meduza_ai/__init__.py
meduza_ai.egg-info/PKG-INFO
meduza_ai.egg-info/SOURCES.txt
meduza_ai.egg-info/dependency_links.txt
meduza_ai.egg-info/top_level.txt