Metadata-Version: 2.4
Name: meduza-ai
Version: 0.0.1
Summary: Build AI Agent - coming soon
Author: Matt Aliev
Requires-Python: >=3.9
Dynamic: author
Dynamic: requires-python
Dynamic: summary
